travel_backpack/__init__.py
travel_backpack/decorators.py
travel_backpack/exceptions.py
travel_backpack/graph.py
travel_backpack/logging.py
travel_backpack/parallel.py
travel_backpack/plotly_visualize.py
travel_backpack/time.py
travel_backpack/variables.py
travel_backpack-3.4.3.dist-info/LICENSE
travel_backpack-3.4.3.dist-info/WHEEL
travel_backpack-3.4.3.dist-info/METADATA
travel_backpack-3.4.3.dist-info/RECORD
