Metadata-Version: 2.1
Name: travel-backpack
Version: 3.4.3
Summary: Some very useful functions and classes to use in day-to-day
Home-page: https://github.com/vMarcelino/travel-backpack
License: Apache-2.0
Author: Victor Marcelino
Requires-Python: >=3.6
Classifier: License :: OSI Approved :: Apache Software License
Classifier: Programming Language :: Python :: 3
Classifier: Programming Language :: Python :: 3.6
Classifier: Programming Language :: Python :: 3.7
Classifier: Programming Language :: Python :: 3.8
Classifier: Programming Language :: Python :: 3.9
